setup.py
Eve_Mongoengine.egg-info/PKG-INFO
Eve_Mongoengine.egg-info/SOURCES.txt
Eve_Mongoengine.egg-info/dependency_links.txt
Eve_Mongoengine.egg-info/not-zip-safe
Eve_Mongoengine.egg-info/requires.txt
Eve_Mongoengine.egg-info/top_level.txt
eve_mongoengine/__init__.py
eve_mongoengine/_compat.py
eve_mongoengine/datalayer.py
eve_mongoengine/schema.py
eve_mongoengine/struct.py
eve_mongoengine/validation.py