Metadata-Version: 1.0
Name: Eve-Mongoengine
Version: 0.0.4
Summary: An Eve extension for Mongoengine ODM support
Home-page: https://github.com/hellerstanislav/eve-mongoengine
Author: Stanislav Heller
Author-email: heller.stanislav@gmail.com
License: UNKNOWN
Platform: any
